langchain_vmxai/__init__.py
langchain_vmxai/chat_models/__init__.py
langchain_vmxai/chat_models/base.py
langchain_vmxai/output_parsers/__init__.py
langchain_vmxai/output_parsers/tools.py
langchain_vmxai/utils/function_calling.py
langchain_vm_x_ai-1.2.6.dist-info/METADATA
langchain_vm_x_ai-1.2.6.dist-info/WHEEL
langchain_vm_x_ai-1.2.6.dist-info/RECORD
