Metadata-Version: 2.1
Name: langchain-vm-x-ai
Version: 1.2.6
Summary: VM-X AI Langchain Python SDK
Home-page: https://github.com/vm-x-ai/vm-x-ai-sdk
License: MIT
Keywords: VM-X,AI,SDK,Python,LangChain
Author: VM-X Engineering
Author-email: eng@vm-x.ai
Maintainer: VM-X Engineering
Maintainer-email: eng@vm-x.ai
Requires-Python: >=3.9,<4
Classifier: Intended Audience :: Developers
Classifier: License :: OSI Approved :: MIT License
Classifier: Programming Language :: Python :: 3
Classifier: Programming Language :: Python :: 3.9
Classifier: Programming Language :: Python :: 3.10
Classifier: Programming Language :: Python :: 3.11
Classifier: Programming Language :: Python :: 3.12
Requires-Dist: langchain-core (>=0.2.29,<0.3.0)
Requires-Dist: vm-x-ai-sdk (==1.7.0)
Project-URL: Repository, https://github.com/vm-x-ai/vm-x-ai-sdk
